CHANGELOG.txt
DESCRIPTION
LICENSE
MANIFEST.in
README.rst
setup.py
django_rest_hooks_delivery.egg-info/PKG-INFO
django_rest_hooks_delivery.egg-info/SOURCES.txt
django_rest_hooks_delivery.egg-info/dependency_links.txt
django_rest_hooks_delivery.egg-info/requires.txt
django_rest_hooks_delivery.egg-info/top_level.txt
rest_hooks_delivery/__init__.py
rest_hooks_delivery/admin.py
rest_hooks_delivery/apps.py
rest_hooks_delivery/deliverers.py
rest_hooks_delivery/models.py
rest_hooks_delivery/management/__init__.py
rest_hooks_delivery/management/commands/__init__.py
rest_hooks_delivery/management/commands/retry_failed_hooks.py
rest_hooks_delivery/migrations/0001_initial.py
rest_hooks_delivery/migrations/__init__.py
rest_hooks_delivery/templates/admin/rest_hooks_delivery/failedhook/change_form.html