Metadata-Version: 1.1
Name: django-rest-hooks-delivery
Version: 0.2.1
Summary: Various webhook deliverers for django-rest-hooks and django-rest-hooks-ng.
Home-page: http://github.com/PressLabs/django-rest-hooks-delivery
Author: PressLabs
Author-email: ping@presslabs.com
License: UNKNOWN
Platform: UNKNOWN
Classifier: Development Status :: 4 - Beta
Classifier: Environment :: Web Environment
Classifier: Framework :: Django
Classifier: Intended Audience :: Developers
Classifier: License :: OSI Approved :: MIT License
Classifier: Operating System :: OS Independent
Classifier: Programming Language :: Python
Classifier: Topic :: Utilities
